aliyunsdkalb/__init__.py
aliyunsdkalb/endpoint.py
aliyunsdkalb/request/__init__.py
aliyunsdkalb/request/v20200616/AddEntriesToAclRequest.py
aliyunsdkalb/request/v20200616/AddServersToServerGroupRequest.py
aliyunsdkalb/request/v20200616/ApplyHealthCheckTemplateToServerGroupRequest.py
aliyunsdkalb/request/v20200616/AssociateAclsWithListenerRequest.py
aliyunsdkalb/request/v20200616/AssociateAdditionalCertificatesWithListenerRequest.py
aliyunsdkalb/request/v20200616/AttachCommonBandwidthPackageToLoadBalancerRequest.py
aliyunsdkalb/request/v20200616/CancelShiftLoadBalancerZonesRequest.py
aliyunsdkalb/request/v20200616/CreateAScriptsRequest.py
aliyunsdkalb/request/v20200616/CreateAclRequest.py
aliyunsdkalb/request/v20200616/CreateHealthCheckTemplateRequest.py
aliyunsdkalb/request/v20200616/CreateListenerRequest.py
aliyunsdkalb/request/v20200616/CreateLoadBalancerRequest.py
aliyunsdkalb/request/v20200616/CreateRuleRequest.py
aliyunsdkalb/request/v20200616/CreateRulesRequest.py
aliyunsdkalb/request/v20200616/CreateSecurityPolicyRequest.py
aliyunsdkalb/request/v20200616/CreateServerGroupRequest.py
aliyunsdkalb/request/v20200616/DeleteAScriptsRequest.py
aliyunsdkalb/request/v20200616/DeleteAclRequest.py
aliyunsdkalb/request/v20200616/DeleteHealthCheckTemplatesRequest.py
aliyunsdkalb/request/v20200616/DeleteListenerRequest.py
aliyunsdkalb/request/v20200616/DeleteLoadBalancerRequest.py
aliyunsdkalb/request/v20200616/DeleteRuleRequest.py
aliyunsdkalb/request/v20200616/DeleteRulesRequest.py
aliyunsdkalb/request/v20200616/DeleteSecurityPolicyRequest.py
aliyunsdkalb/request/v20200616/DeleteServerGroupRequest.py
aliyunsdkalb/request/v20200616/DescribeRegionsRequest.py
aliyunsdkalb/request/v20200616/DescribeZonesRequest.py
aliyunsdkalb/request/v20200616/DetachCommonBandwidthPackageFromLoadBalancerRequest.py
aliyunsdkalb/request/v20200616/DisableDeletionProtectionRequest.py
aliyunsdkalb/request/v20200616/DisableLoadBalancerAccessLogRequest.py
aliyun_python_sdk_alb-1.0.22.dist-info/LICENSE
aliyun_python_sdk_alb-1.0.22.dist-info/METADATA
aliyun_python_sdk_alb-1.0.22.dist-info/WHEEL
aliyun_python_sdk_alb-1.0.22.dist-info/top_level.txt
aliyun_python_sdk_alb-1.0.22.dist-info/RECORD
